posecraft/Pose.py
posecraft/__init__.py
posecraft/interpolate.py
posecraft/transforms.py
posecraft/assets/hands_dict.png
posecraft/assets/pose_dict.png
posecraft-1.0.1rc93.post1.dist-info/LICENSE
posecraft-1.0.1rc93.post1.dist-info/WHEEL
posecraft-1.0.1rc93.post1.dist-info/METADATA
posecraft-1.0.1rc93.post1.dist-info/RECORD
