Metadata-Version: 2.3
Name: posecraft
Version: 1.0.1rc93.post1
Summary: Library for manipulating pose keypoints
Author-email: Pedro Dal Bianco <dalbianco.pedro@gmail.com>
Requires-Python: >=3.9
Classifier: Development Status :: 3 - Alpha
Classifier: Intended Audience :: Developers
Classifier: License :: OSI Approved :: MIT License
Classifier: Programming Language :: Python :: 3 :: Only
Classifier: Programming Language :: Python :: 3.9
Classifier: Programming Language :: Python :: 3.10
Classifier: Programming Language :: Python :: 3.11
Requires-Dist: pyspark>=3.0.0 ; extra == "spark"
Requires-Dist: bandit[toml]==1.8.2 ; extra == "test"
Requires-Dist: black==24.10.0 ; extra == "test"
Requires-Dist: check-manifest==0.50 ; extra == "test"
Requires-Dist: flake8-bugbear==24.12.12 ; extra == "test"
Requires-Dist: flake8-docstrings ; extra == "test"
Requires-Dist: flake8-formatter_junit_xml ; extra == "test"
Requires-Dist: flake8 ; extra == "test"
Requires-Dist: flake8-pyproject ; extra == "test"
Requires-Dist: matplotlib==3.8.3 ; extra == "test"
Requires-Dist: numpy==1.26.4 ; extra == "test"
Requires-Dist: pre-commit==4.1.0 ; extra == "test"
Requires-Dist: pylint==3.3.3 ; extra == "test"
Requires-Dist: pylint_junit ; extra == "test"
Requires-Dist: pytest-mock<3.14.1 ; extra == "test"
Requires-Dist: pytest-cov==6.0.0 ; extra == "test"
Requires-Dist: pytest-runner ; extra == "test"
Requires-Dist: pytest==8.3.4 ; extra == "test"
Requires-Dist: pytest-github-actions-annotate-failures ; extra == "test"
Requires-Dist: shellcheck-py==0.10.0.1 ; extra == "test"
Requires-Dist: torch==2.3.1 ; extra == "test"
Requires-Dist: torchvision==0.18.1 ; extra == "test"
Project-URL: Documentation, https://github.com/microsoft/posecraft/tree/main#readme
Project-URL: Source, https://github.com/microsoft/posecraft
Project-URL: Tracker, https://github.com/microsoft/posecraft/issues
Provides-Extra: spark
Provides-Extra: test
